nonstd/__init__.py
nonstd/derivative.py
nonstd/logging.py
nonstd/representation.py
nonstd/sequence.py
nonstd/sequence_math.py
nonstd/timer.py
nonstd-0.0.8.dist-info/METADATA
nonstd-0.0.8.dist-info/WHEEL
nonstd-0.0.8.dist-info/RECORD
